shaml/__init__.py
shaml/__main__.py
shaml/core.py
shaml-0.0.2.dist-info/METADATA
shaml-0.0.2.dist-info/WHEEL
shaml-0.0.2.dist-info/top_level.txt
shaml-0.0.2.dist-info/RECORD
