Metadata-Version: 2.1
Name: shaml
Version: 0.0.2
Summary: A shameless library for auto-correcting variable types.
Home-page: https://github.com/mgks/shaml
Author: Ghazi Khan
Author-email: hello@mgks.dev
License: MIT
Platform: UNKNOWN
